{"geojson": {"type": "Feature", "geometry": {"type": "Point", "coordinates": [-75.1652, 39.9526]}, "properties": {"Year Built": "1987", "Total Square Feet Living Area": "2,184", "Building Style": "COLONIAL", "Exterior Wall Material": "ALUMINUM/VINYL SIDING", "Heating Fuel Type": "ELECTRIC", "Heating System Type": "WARM AIR", "Heat/Air Cond": "AIR COND", "Bedrooms": "4", "Full Baths": "2", "Half Baths": "1", "Basement": "FULL", "Number of Stories": "2", "Grade": "B - GOOD"}}, "inspection_note": "The home, built in 1987, features aluminum/vinyl siding which appears to be in good condition. The electric warm air heating system is paired with air conditioning, suggesting a well-maintained HVAC system. The windows seem relatively modern, likely double-glazed, aiding in energy efficiency. The full basement is a plus for insulation, though further inspection of its sealing is recommended. Overall, the property reflects a colonial style with good energy efficiency features for its age.", "weather": "KABE"}